donkit/read_engine/README.md
donkit/read_engine/__init__.py
donkit/read_engine/read_engine.py
donkit/read_engine/readers/__init__.py
donkit/read_engine/readers/json_document_format/__init__.py
donkit/read_engine/readers/json_document_format/handler.py
donkit/read_engine/readers/microsoft_office_document/__init__.py
donkit/read_engine/readers/microsoft_office_document/handler.py
donkit/read_engine/readers/microsoft_office_document/parser.py
donkit/read_engine/readers/microsoft_office_presentation/__init__.py
donkit/read_engine/readers/microsoft_office_presentation/handler.py
donkit/read_engine/readers/microsoft_office_sheet/__init__.py
donkit/read_engine/readers/microsoft_office_sheet/handler.py
donkit/read_engine/readers/portable_document_format/__init__.py
donkit/read_engine/readers/portable_document_format/handler.py
donkit/read_engine/readers/portable_document_format/pdf_parser.py
donkit/read_engine/readers/static_visual_format/__init__.py
donkit/read_engine/readers/static_visual_format/handler.py
donkit/read_engine/readers/static_visual_format/models.py
donkit/read_engine/readers/text_document_format/__init__.py
donkit/read_engine/readers/text_document_format/handler.py
donkit_read_engine-0.2.8.dist-info/METADATA
donkit_read_engine-0.2.8.dist-info/WHEEL
donkit_read_engine-0.2.8.dist-info/entry_points.txt
donkit_read_engine-0.2.8.dist-info/RECORD
