Metadata-Version: 2.3
Name: donkit-read-engine
Version: 0.2.8
Summary: Document loading helpers for Donkit RagOps
License: MIT
Author: Donkit AI
Author-email: opensource@donkit.ai
Requires-Python: >=3.12,<3.14
Classifier: License :: OSI Approved :: MIT License
Classifier: Programming Language :: Python :: 3
Classifier: Programming Language :: Python :: 3.12
Classifier: Programming Language :: Python :: 3.13
Requires-Dist: asyncio (>=3.4.3,<4.0.0)
Requires-Dist: docling (>=2.55.1,<3.0.0)
Requires-Dist: donkit-llm (>=0.1.4,<0.2.0)
Requires-Dist: json-repair (>=0.52.3,<0.53.0)
Requires-Dist: loguru (>=0.7.2,<0.8.0)
Requires-Dist: pandas (>=2.2.3,<3.0.0)
Requires-Dist: pillow (>=10.2.0,<11.0.0)
Requires-Dist: pymupdf (>=1.26.4,<2.0.0)
Requires-Dist: pypdf (>=6.1.3,<7.0.0)
Requires-Dist: python-docx (>=1.1.0,<2.0.0)
Requires-Dist: python-dotenv (>=1.1.0,<2.0.0)
Requires-Dist: python-pptx (>=1.0.2,<2.0.0)
Requires-Dist: unstructured[pdf] (>=0.18.15,<0.19.0)
